imuthes/alchemy/types/__init__.py
imuthes/alchemy/types/big_integer.py
imuthes/alchemy/types/medium_integer.py
imuthes/alchemy/types/small_integer.py
imuthes/alchemy/types/tiny_integer.py
imuthes/alchemy/types/unsigned_big_integer.py
imuthes/alchemy/types/unsigned_integer.py
imuthes/alchemy/types/unsigned_medium_integer.py
imuthes/alchemy/types/unsigned_small_integer.py
imuthes/alchemy/types/unsigned_tiny_integer.py
imuthes_alchemy_types-0.0.0a0.dist-info/METADATA
imuthes_alchemy_types-0.0.0a0.dist-info/WHEEL
imuthes_alchemy_types-0.0.0a0.dist-info/RECORD
